laser_measles/core.py
laser_measles/_core.cpython-312-x86_64-linux-musl.so
laser_measles/_core.c
laser_measles/cli.py
laser_measles/__main__.py
laser_measles/utils.py
laser_measles/model.py
laser_measles/api.py
laser_measles/measles.md
laser_measles/infection.py
laser_measles/__init__.py
laser_measles/routine.py
laser_measles/susceptibility.py
laser_measles/mortality.py
laser_measles/antibodies.py
laser_measles/births.py
laser_measles/incubation.py
laser_measles/transmission.py
laser_measles/demographics/cache.py
laser_measles/demographics/raster_patch.py
laser_measles/demographics/gadm.py
laser_measles/demographics/base.py
laser_measles/demographics/__init__.py
laser_measles/demographics/admin_shapefile.py
laser_measles/demographics/shapefiles.py
laser_measles/nigeria/lgas.py
laser_measles/nigeria/model.py
laser_measles/nigeria/nigeria_pyramid.csv
laser_measles/nigeria/__init__.py
laser_measles/nigeria/metapop.py
laser_measles/nigeria/params.py
laser_measles/nigeria/nigeria_mortality.csv
laser_measles/nigeria/northern-nigeria/northern-nigeria.prj
laser_measles/nigeria/northern-nigeria/northern-nigeria.shp
laser_measles/nigeria/northern-nigeria/northern-nigeria.cpg
laser_measles/nigeria/northern-nigeria/northern-nigeria.dbf
laser_measles/nigeria/northern-nigeria/northern-nigeria.shx
laser_measles/nigeria/nga_adm_osgof_20190417/nga_admbnda_adm2_osgof_20190417.sbn
laser_measles/nigeria/nga_adm_osgof_20190417/nga_admbnda_adm2_osgof_20190417.prj
laser_measles/nigeria/nga_adm_osgof_20190417/nga_admbnda_adm2_osgof_20190417.CPG
laser_measles/nigeria/nga_adm_osgof_20190417/nga_admbnda_adm2_osgof_20190417.dbf
laser_measles/nigeria/nga_adm_osgof_20190417/nga_admbnda_adm2_osgof_20190417.shp
laser_measles/nigeria/nga_adm_osgof_20190417/nga_admbnda_adm2_osgof_20190417.shx
laser_measles/nigeria/nga_adm_osgof_20190417/nga_admbnda_adm2_osgof_20190417.sbx
laser_measles-0.6.3.dist-info/top_level.txt
laser_measles-0.6.3.dist-info/RECORD
laser_measles-0.6.3.dist-info/METADATA
laser_measles-0.6.3.dist-info/entry_points.txt
laser_measles-0.6.3.dist-info/WHEEL
laser_measles-0.6.3.dist-info/licenses/AUTHORS.rst
laser_measles-0.6.3.dist-info/licenses/LICENSE
